MANIFEST.in
NEWS.txt
README.rst
setup.py
src/dardrive/__init__.py
src/dardrive/cmdp.py
src/dardrive/config.py
src/dardrive/dar.py
src/dardrive/db.py
src/dardrive/excepts.py
src/dardrive/shell.py
src/dardrive/utils.py
src/dardrive.egg-info/PKG-INFO
src/dardrive.egg-info/SOURCES.txt
src/dardrive.egg-info/dependency_links.txt
src/dardrive.egg-info/entry_points.txt
src/dardrive.egg-info/not-zip-safe
src/dardrive.egg-info/requires.txt
src/dardrive.egg-info/top_level.txt
src/dardrive/tests/__init__.py
src/dardrive/tests/config.py
src/dardrive/tests/darsetts.py
src/dardrive/tests/last_run.py
src/dardrive/tests/locks.py
src/dardrive/tests/purge.py
src/dardrive/tests/stats.py
src/dardrive/tests/test.cfg
src/dardrive/tests/validators.py
src/dardrive/tests/xattr.py