Metadata-Version: 1.1
Name: dardrive
Version: 0.2.11b13
Summary: A dar based backup tool
Home-page: http://jfardello.github.com/Dardrive/
Author: José Manuel Fardello
Author-email: jmfardello@gmail.com
License: GPLv3
Download-URL: http://pypi.python.org/pypi/dardrive
Keywords: dar cli backup python cloud
Platform: UNKNOWN
Classifier: Development Status :: 4 - Beta
Classifier: Intended Audience :: System Administrators
Classifier: License :: OSI Approved :: MIT License
Classifier: Operating System :: POSIX :: Linux
Classifier: Programming Language :: Python :: 2.7
Classifier: Topic :: System :: Archiving :: Backup
